package io.xlink.wifi.sdk;

class XlinkTcpService$5 extends Thread
{
  XlinkTcpService$5(XlinkTcpService paramXlinkTcpService)
  {
  }

  // ERROR //
  public void run()
  {
    // Byte code:
    //   0: aload_0
    //   1: invokespecial 26	java/lang/Thread:run	()V
    //   4: invokestatic 30	io/xlink/wifi/sdk/XlinkTcpService:c	()Z
    //   7: ifeq +13 -> 20
    //   10: aload_0
    //   11: getfield 15	io/xlink/wifi/sdk/XlinkTcpService$5:a	Lio/xlink/wifi/sdk/XlinkTcpService;
    //   14: ldc 32
    //   16: invokestatic 35	io/xlink/wifi/sdk/XlinkTcpService:a	(Lio/xlink/wifi/sdk/XlinkTcpService;Ljava/lang/String;)V
    //   19: return
    //   20: aload_0
    //   21: getfield 15	io/xlink/wifi/sdk/XlinkTcpService$5:a	Lio/xlink/wifi/sdk/XlinkTcpService;
    //   24: invokestatic 39	io/xlink/wifi/sdk/XlinkTcpService:f	(Lio/xlink/wifi/sdk/XlinkTcpService;)Z
    //   27: ifeq +26 -> 53
    //   30: getstatic 42	io/xlink/wifi/sdk/XlinkTcpService:a	I
    //   33: ifeq +20 -> 53
    //   36: aload_0
    //   37: getfield 15	io/xlink/wifi/sdk/XlinkTcpService$5:a	Lio/xlink/wifi/sdk/XlinkTcpService;
    //   40: ldc 44
    //   42: invokestatic 35	io/xlink/wifi/sdk/XlinkTcpService:a	(Lio/xlink/wifi/sdk/XlinkTcpService;Ljava/lang/String;)V
    //   45: aload_0
    //   46: getfield 15	io/xlink/wifi/sdk/XlinkTcpService$5:a	Lio/xlink/wifi/sdk/XlinkTcpService;
    //   49: invokestatic 47	io/xlink/wifi/sdk/XlinkTcpService:g	(Lio/xlink/wifi/sdk/XlinkTcpService;)V
    //   52: return
    //   53: aload_0
    //   54: getfield 15	io/xlink/wifi/sdk/XlinkTcpService$5:a	Lio/xlink/wifi/sdk/XlinkTcpService;
    //   57: new 49	java/lang/StringBuilder
    //   60: dup
    //   61: invokespecial 50	java/lang/StringBuilder:<init>	()V
    //   64: ldc 52
    //   66: invokevirtual 56	java/lang/StringBuilder:append	(Ljava/lang/String;)Ljava/lang/StringBuilder;
    //   69: getstatic 61	io/xlink/wifi/sdk/global/a:a	Ljava/lang/String;
    //   72: invokevirtual 56	java/lang/StringBuilder:append	(Ljava/lang/String;)Ljava/lang/StringBuilder;
    //   75: invokevirtual 65	java/lang/StringBuilder:toString	()Ljava/lang/String;
    //   78: invokestatic 35	io/xlink/wifi/sdk/XlinkTcpService:a	(Lio/xlink/wifi/sdk/XlinkTcpService;Ljava/lang/String;)V
    //   81: aload_0
    //   82: getfield 15	io/xlink/wifi/sdk/XlinkTcpService$5:a	Lio/xlink/wifi/sdk/XlinkTcpService;
    //   85: invokestatic 68	io/xlink/wifi/sdk/XlinkTcpService:c	(Lio/xlink/wifi/sdk/XlinkTcpService;)Ljava/net/InetAddress;
    //   88: ifnonnull +37 -> 125
    //   91: new 70	io/xlink/wifi/sdk/util/a
    //   94: dup
    //   95: getstatic 61	io/xlink/wifi/sdk/global/a:a	Ljava/lang/String;
    //   98: invokespecial 73	io/xlink/wifi/sdk/util/a:<init>	(Ljava/lang/String;)V
    //   101: astore_3
    //   102: aload_3
    //   103: invokevirtual 76	io/xlink/wifi/sdk/util/a:start	()V
    //   106: aload_3
    //   107: ldc2_w 77
    //   110: invokevirtual 82	io/xlink/wifi/sdk/util/a:join	(J)V
    //   113: aload_0
    //   114: getfield 15	io/xlink/wifi/sdk/XlinkTcpService$5:a	Lio/xlink/wifi/sdk/XlinkTcpService;
    //   117: aload_3
    //   118: invokevirtual 85	io/xlink/wifi/sdk/util/a:a	()Ljava/net/InetAddress;
    //   121: invokestatic 88	io/xlink/wifi/sdk/XlinkTcpService:a	(Lio/xlink/wifi/sdk/XlinkTcpService;Ljava/net/InetAddress;)Ljava/net/InetAddress;
    //   124: pop
    //   125: aload_0
    //   126: getfield 15	io/xlink/wifi/sdk/XlinkTcpService$5:a	Lio/xlink/wifi/sdk/XlinkTcpService;
    //   129: invokestatic 68	io/xlink/wifi/sdk/XlinkTcpService:c	(Lio/xlink/wifi/sdk/XlinkTcpService;)Ljava/net/InetAddress;
    //   132: ifnonnull +123 -> 255
    //   135: new 20	java/net/UnknownHostException
    //   138: dup
    //   139: new 49	java/lang/StringBuilder
    //   142: dup
    //   143: invokespecial 50	java/lang/StringBuilder:<init>	()V
    //   146: ldc 90
    //   148: invokevirtual 56	java/lang/StringBuilder:append	(Ljava/lang/String;)Ljava/lang/StringBuilder;
    //   151: getstatic 61	io/xlink/wifi/sdk/global/a:a	Ljava/lang/String;
    //   154: invokevirtual 56	java/lang/StringBuilder:append	(Ljava/lang/String;)Ljava/lang/StringBuilder;
    //   157: ldc 92
    //   159: invokevirtual 56	java/lang/StringBuilder:append	(Ljava/lang/String;)Ljava/lang/StringBuilder;
    //   162: invokevirtual 65	java/lang/StringBuilder:toString	()Ljava/lang/String;
    //   165: invokespecial 93	java/net/UnknownHostException:<init>	(Ljava/lang/String;)V
    //   168: athrow
    //   169: astore_2
    //   170: iconst_0
    //   171: putstatic 97	io/xlink/wifi/sdk/XlinkTcpService:d	Z
    //   174: aload_0
    //   175: getfield 15	io/xlink/wifi/sdk/XlinkTcpService$5:a	Lio/xlink/wifi/sdk/XlinkTcpService;
    //   178: ldc 99
    //   180: invokestatic 35	io/xlink/wifi/sdk/XlinkTcpService:a	(Lio/xlink/wifi/sdk/XlinkTcpService;Ljava/lang/String;)V
    //   183: iconst_5
    //   184: iconst_m1
    //   185: invokestatic 104	io/xlink/wifi/sdk/event/c:a	(II)V
    //   188: aload_0
    //   189: getfield 15	io/xlink/wifi/sdk/XlinkTcpService$5:a	Lio/xlink/wifi/sdk/XlinkTcpService;
    //   192: invokestatic 107	io/xlink/wifi/sdk/XlinkTcpService:e	(Lio/xlink/wifi/sdk/XlinkTcpService;)V
    //   195: return
    //   196: astore 4
    //   198: aload 4
    //   200: invokevirtual 110	java/lang/InterruptedException:printStackTrace	()V
    //   203: goto -90 -> 113
    //   206: astore_1
    //   207: aload_0
    //   208: getfield 15	io/xlink/wifi/sdk/XlinkTcpService$5:a	Lio/xlink/wifi/sdk/XlinkTcpService;
    //   211: ldc 112
    //   213: invokestatic 35	io/xlink/wifi/sdk/XlinkTcpService:a	(Lio/xlink/wifi/sdk/XlinkTcpService;Ljava/lang/String;)V
    //   216: getstatic 115	io/xlink/wifi/sdk/global/a:i	I
    //   219: iconst_1
    //   220: if_icmpne +285 -> 505
    //   223: iconst_0
    //   224: putstatic 97	io/xlink/wifi/sdk/XlinkTcpService:d	Z
    //   227: getstatic 118	io/xlink/wifi/sdk/XlinkTcpService:j	I
    //   230: iconst_1
    //   231: if_icmpne +220 -> 451
    //   234: aload_0
    //   235: getfield 15	io/xlink/wifi/sdk/XlinkTcpService$5:a	Lio/xlink/wifi/sdk/XlinkTcpService;
    //   238: ldc 120
    //   240: invokestatic 35	io/xlink/wifi/sdk/XlinkTcpService:a	(Lio/xlink/wifi/sdk/XlinkTcpService;Ljava/lang/String;)V
    //   243: iconst_3
    //   244: putstatic 118	io/xlink/wifi/sdk/XlinkTcpService:j	I
    //   247: aload_0
    //   248: getfield 15	io/xlink/wifi/sdk/XlinkTcpService$5:a	Lio/xlink/wifi/sdk/XlinkTcpService;
    //   251: invokestatic 123	io/xlink/wifi/sdk/XlinkTcpService:b	(Lio/xlink/wifi/sdk/XlinkTcpService;)V
    //   254: return
    //   255: aload_0
    //   256: getfield 15	io/xlink/wifi/sdk/XlinkTcpService$5:a	Lio/xlink/wifi/sdk/XlinkTcpService;
    //   259: new 125	java/net/Socket
    //   262: dup
    //   263: invokespecial 126	java/net/Socket:<init>	()V
    //   266: invokestatic 129	io/xlink/wifi/sdk/XlinkTcpService:a	(Lio/xlink/wifi/sdk/XlinkTcpService;Ljava/net/Socket;)Ljava/net/Socket;
    //   269: pop
    //   270: getstatic 115	io/xlink/wifi/sdk/global/a:i	I
    //   273: iconst_3
    //   274: if_icmpeq +10 -> 284
    //   277: getstatic 118	io/xlink/wifi/sdk/XlinkTcpService:j	I
    //   280: iconst_3
    //   281: if_icmpne +97 -> 378
    //   284: aload_0
    //   285: getfield 15	io/xlink/wifi/sdk/XlinkTcpService$5:a	Lio/xlink/wifi/sdk/XlinkTcpService;
    //   288: new 49	java/lang/StringBuilder
    //   291: dup
    //   292: invokespecial 50	java/lang/StringBuilder:<init>	()V
    //   295: ldc 131
    //   297: invokevirtual 56	java/lang/StringBuilder:append	(Ljava/lang/String;)Ljava/lang/StringBuilder;
    //   300: aload_0
    //   301: getfield 15	io/xlink/wifi/sdk/XlinkTcpService$5:a	Lio/xlink/wifi/sdk/XlinkTcpService;
    //   304: invokestatic 68	io/xlink/wifi/sdk/XlinkTcpService:c	(Lio/xlink/wifi/sdk/XlinkTcpService;)Ljava/net/InetAddress;
    //   307: invokevirtual 134	java/net/InetAddress:toString	()Ljava/lang/String;
    //   310: invokevirtual 56	java/lang/StringBuilder:append	(Ljava/lang/String;)Ljava/lang/StringBuilder;
    //   313: ldc 136
    //   315: invokevirtual 56	java/lang/StringBuilder:append	(Ljava/lang/String;)Ljava/lang/StringBuilder;
    //   318: invokevirtual 65	java/lang/StringBuilder:toString	()Ljava/lang/String;
    //   321: invokestatic 35	io/xlink/wifi/sdk/XlinkTcpService:a	(Lio/xlink/wifi/sdk/XlinkTcpService;Ljava/lang/String;)V
    //   324: aload_0
    //   325: getfield 15	io/xlink/wifi/sdk/XlinkTcpService$5:a	Lio/xlink/wifi/sdk/XlinkTcpService;
    //   328: invokestatic 139	io/xlink/wifi/sdk/XlinkTcpService:d	(Lio/xlink/wifi/sdk/XlinkTcpService;)Ljava/net/Socket;
    //   331: new 141	java/net/InetSocketAddress
    //   334: dup
    //   335: aload_0
    //   336: getfield 15	io/xlink/wifi/sdk/XlinkTcpService$5:a	Lio/xlink/wifi/sdk/XlinkTcpService;
    //   339: invokestatic 68	io/xlink/wifi/sdk/XlinkTcpService:c	(Lio/xlink/wifi/sdk/XlinkTcpService;)Ljava/net/InetAddress;
    //   342: getstatic 143	io/xlink/wifi/sdk/global/a:d	I
    //   345: invokespecial 146	java/net/InetSocketAddress:<init>	(Ljava/net/InetAddress;I)V
    //   348: sipush 8000
    //   351: invokevirtual 150	java/net/Socket:connect	(Ljava/net/SocketAddress;I)V
    //   354: aload_0
    //   355: getfield 15	io/xlink/wifi/sdk/XlinkTcpService$5:a	Lio/xlink/wifi/sdk/XlinkTcpService;
    //   358: aload_0
    //   359: getfield 15	io/xlink/wifi/sdk/XlinkTcpService$5:a	Lio/xlink/wifi/sdk/XlinkTcpService;
    //   362: invokestatic 139	io/xlink/wifi/sdk/XlinkTcpService:d	(Lio/xlink/wifi/sdk/XlinkTcpService;)Ljava/net/Socket;
    //   365: invokestatic 153	io/xlink/wifi/sdk/XlinkTcpService:b	(Lio/xlink/wifi/sdk/XlinkTcpService;Ljava/net/Socket;)V
    //   368: aload_0
    //   369: getfield 15	io/xlink/wifi/sdk/XlinkTcpService$5:a	Lio/xlink/wifi/sdk/XlinkTcpService;
    //   372: ldc 155
    //   374: invokestatic 35	io/xlink/wifi/sdk/XlinkTcpService:a	(Lio/xlink/wifi/sdk/XlinkTcpService;Ljava/lang/String;)V
    //   377: return
    //   378: aload_0
    //   379: getfield 15	io/xlink/wifi/sdk/XlinkTcpService$5:a	Lio/xlink/wifi/sdk/XlinkTcpService;
    //   382: new 49	java/lang/StringBuilder
    //   385: dup
    //   386: invokespecial 50	java/lang/StringBuilder:<init>	()V
    //   389: ldc 131
    //   391: invokevirtual 56	java/lang/StringBuilder:append	(Ljava/lang/String;)Ljava/lang/StringBuilder;
    //   394: aload_0
    //   395: getfield 15	io/xlink/wifi/sdk/XlinkTcpService$5:a	Lio/xlink/wifi/sdk/XlinkTcpService;
    //   398: invokestatic 68	io/xlink/wifi/sdk/XlinkTcpService:c	(Lio/xlink/wifi/sdk/XlinkTcpService;)Ljava/net/InetAddress;
    //   401: invokevirtual 134	java/net/InetAddress:toString	()Ljava/lang/String;
    //   404: invokevirtual 56	java/lang/StringBuilder:append	(Ljava/lang/String;)Ljava/lang/StringBuilder;
    //   407: ldc 157
    //   409: invokevirtual 56	java/lang/StringBuilder:append	(Ljava/lang/String;)Ljava/lang/StringBuilder;
    //   412: invokevirtual 65	java/lang/StringBuilder:toString	()Ljava/lang/String;
    //   415: invokestatic 35	io/xlink/wifi/sdk/XlinkTcpService:a	(Lio/xlink/wifi/sdk/XlinkTcpService;Ljava/lang/String;)V
    //   418: aload_0
    //   419: getfield 15	io/xlink/wifi/sdk/XlinkTcpService$5:a	Lio/xlink/wifi/sdk/XlinkTcpService;
    //   422: invokestatic 139	io/xlink/wifi/sdk/XlinkTcpService:d	(Lio/xlink/wifi/sdk/XlinkTcpService;)Ljava/net/Socket;
    //   425: new 141	java/net/InetSocketAddress
    //   428: dup
    //   429: aload_0
    //   430: getfield 15	io/xlink/wifi/sdk/XlinkTcpService$5:a	Lio/xlink/wifi/sdk/XlinkTcpService;
    //   433: invokestatic 68	io/xlink/wifi/sdk/XlinkTcpService:c	(Lio/xlink/wifi/sdk/XlinkTcpService;)Ljava/net/InetAddress;
    //   436: getstatic 159	io/xlink/wifi/sdk/global/a:b	I
    //   439: invokespecial 146	java/net/InetSocketAddress:<init>	(Ljava/net/InetAddress;I)V
    //   442: sipush 8000
    //   445: invokevirtual 150	java/net/Socket:connect	(Ljava/net/SocketAddress;I)V
    //   448: goto -94 -> 354
    //   451: getstatic 118	io/xlink/wifi/sdk/XlinkTcpService:j	I
    //   454: iconst_3
    //   455: if_icmpne +24 -> 479
    //   458: aload_0
    //   459: getfield 15	io/xlink/wifi/sdk/XlinkTcpService$5:a	Lio/xlink/wifi/sdk/XlinkTcpService;
    //   462: ldc 161
    //   464: invokestatic 35	io/xlink/wifi/sdk/XlinkTcpService:a	(Lio/xlink/wifi/sdk/XlinkTcpService;Ljava/lang/String;)V
    //   467: iconst_4
    //   468: putstatic 118	io/xlink/wifi/sdk/XlinkTcpService:j	I
    //   471: aload_0
    //   472: getfield 15	io/xlink/wifi/sdk/XlinkTcpService$5:a	Lio/xlink/wifi/sdk/XlinkTcpService;
    //   475: invokestatic 164	io/xlink/wifi/sdk/XlinkTcpService:h	(Lio/xlink/wifi/sdk/XlinkTcpService;)V
    //   478: return
    //   479: aload_0
    //   480: getfield 15	io/xlink/wifi/sdk/XlinkTcpService$5:a	Lio/xlink/wifi/sdk/XlinkTcpService;
    //   483: invokestatic 107	io/xlink/wifi/sdk/XlinkTcpService:e	(Lio/xlink/wifi/sdk/XlinkTcpService;)V
    //   486: iconst_0
    //   487: putstatic 97	io/xlink/wifi/sdk/XlinkTcpService:d	Z
    //   490: aload_0
    //   491: getfield 15	io/xlink/wifi/sdk/XlinkTcpService$5:a	Lio/xlink/wifi/sdk/XlinkTcpService;
    //   494: ldc 112
    //   496: invokestatic 35	io/xlink/wifi/sdk/XlinkTcpService:a	(Lio/xlink/wifi/sdk/XlinkTcpService;Ljava/lang/String;)V
    //   499: iconst_5
    //   500: iconst_m1
    //   501: invokestatic 104	io/xlink/wifi/sdk/event/c:a	(II)V
    //   504: return
    //   505: iconst_0
    //   506: putstatic 97	io/xlink/wifi/sdk/XlinkTcpService:d	Z
    //   509: aload_0
    //   510: getfield 15	io/xlink/wifi/sdk/XlinkTcpService$5:a	Lio/xlink/wifi/sdk/XlinkTcpService;
    //   513: invokestatic 107	io/xlink/wifi/sdk/XlinkTcpService:e	(Lio/xlink/wifi/sdk/XlinkTcpService;)V
    //   516: iconst_5
    //   517: iconst_m1
    //   518: invokestatic 104	io/xlink/wifi/sdk/event/c:a	(II)V
    //   521: return
    //
    // Exception table:
    //   from	to	target	type
    //   53	106	169	java/net/UnknownHostException
    //   106	113	169	java/net/UnknownHostException
    //   113	125	169	java/net/UnknownHostException
    //   125	169	169	java/net/UnknownHostException
    //   198	203	169	java/net/UnknownHostException
    //   255	284	169	java/net/UnknownHostException
    //   284	354	169	java/net/UnknownHostException
    //   354	377	169	java/net/UnknownHostException
    //   378	448	169	java/net/UnknownHostException
    //   106	113	196	java/lang/InterruptedException
    //   53	106	206	java/io/IOException
    //   106	113	206	java/io/IOException
    //   113	125	206	java/io/IOException
    //   125	169	206	java/io/IOException
    //   198	203	206	java/io/IOException
    //   255	284	206	java/io/IOException
    //   284	354	206	java/io/IOException
    //   354	377	206	java/io/IOException
    //   378	448	206	java/io/IOException
  }
}

/* Location:
 * Qualified Name:     io.xlink.wifi.sdk.XlinkTcpService.5
 * Java Class Version: 6 (50.0)
 * JD-Core Version:    0.6.1-SNAPSHOT
 */