package com.irainxun.wifilight.apsetting.model;

import com.irainxun.wifilight.apsetting.net.UdpUnicast.UdpUnicastListener;

abstract class ATCommand$CMDModeTryer
{
  private ATCommand$CMDModeTryer(ATCommand paramATCommand)
  {
  }

  abstract void onResult(boolean paramBoolean);

  // ERROR //
  void toTry(boolean paramBoolean)
  {
    // Byte code:
    //   0: aload_0
    //   1: getfield 10	com/irainxun/wifilight/apsetting/model/ATCommand$CMDModeTryer:this$0	Lcom/irainxun/wifilight/apsetting/model/ATCommand;
    //   4: invokestatic 29	com/irainxun/wifilight/apsetting/model/ATCommand:access$0	(Lcom/irainxun/wifilight/apsetting/model/ATCommand;)Ljava/lang/StringBuffer;
    //   7: iconst_0
    //   8: invokevirtual 35	java/lang/StringBuffer:setLength	(I)V
    //   11: iload_1
    //   12: ifeq +53 -> 65
    //   15: aload_0
    //   16: getfield 10	com/irainxun/wifilight/apsetting/model/ATCommand$CMDModeTryer:this$0	Lcom/irainxun/wifilight/apsetting/model/ATCommand;
    //   19: invokestatic 38	com/irainxun/wifilight/apsetting/model/ATCommand:access$1	(Lcom/irainxun/wifilight/apsetting/model/ATCommand;)Lcom/irainxun/wifilight/apsetting/net/UdpUnicast;
    //   22: new 40	com/irainxun/wifilight/apsetting/model/ATCommand$CMDModeTryer$1
    //   25: dup
    //   26: aload_0
    //   27: invokespecial 43	com/irainxun/wifilight/apsetting/model/ATCommand$CMDModeTryer$1:<init>	(Lcom/irainxun/wifilight/apsetting/model/ATCommand$CMDModeTryer;)V
    //   30: invokevirtual 49	com/irainxun/wifilight/apsetting/net/UdpUnicast:setListener	(Lcom/irainxun/wifilight/apsetting/net/UdpUnicast$UdpUnicastListener;)V
    //   33: aload_0
    //   34: getfield 10	com/irainxun/wifilight/apsetting/model/ATCommand$CMDModeTryer:this$0	Lcom/irainxun/wifilight/apsetting/model/ATCommand;
    //   37: invokestatic 29	com/irainxun/wifilight/apsetting/model/ATCommand:access$0	(Lcom/irainxun/wifilight/apsetting/model/ATCommand;)Ljava/lang/StringBuffer;
    //   40: astore_2
    //   41: aload_2
    //   42: monitorenter
    //   43: aload_0
    //   44: getfield 10	com/irainxun/wifilight/apsetting/model/ATCommand$CMDModeTryer:this$0	Lcom/irainxun/wifilight/apsetting/model/ATCommand;
    //   47: invokestatic 38	com/irainxun/wifilight/apsetting/model/ATCommand:access$1	(Lcom/irainxun/wifilight/apsetting/model/ATCommand;)Lcom/irainxun/wifilight/apsetting/net/UdpUnicast;
    //   50: ldc 51
    //   52: invokevirtual 55	com/irainxun/wifilight/apsetting/net/UdpUnicast:send	(Ljava/lang/String;)Z
    //   55: ifne +11 -> 66
    //   58: aload_0
    //   59: iconst_0
    //   60: invokevirtual 57	com/irainxun/wifilight/apsetting/model/ATCommand$CMDModeTryer:onResult	(Z)V
    //   63: aload_2
    //   64: monitorexit
    //   65: return
    //   66: aload_0
    //   67: getfield 10	com/irainxun/wifilight/apsetting/model/ATCommand$CMDModeTryer:this$0	Lcom/irainxun/wifilight/apsetting/model/ATCommand;
    //   70: invokestatic 29	com/irainxun/wifilight/apsetting/model/ATCommand:access$0	(Lcom/irainxun/wifilight/apsetting/model/ATCommand;)Ljava/lang/StringBuffer;
    //   73: ldc2_w 58
    //   76: invokevirtual 63	java/lang/Object:wait	(J)V
    //   79: aload_2
    //   80: monitorexit
    //   81: ldc 65
    //   83: new 67	java/lang/StringBuilder
    //   86: dup
    //   87: ldc 69
    //   89: invokespecial 72	java/lang/StringBuilder:<init>	(Ljava/lang/String;)V
    //   92: aload_0
    //   93: getfield 10	com/irainxun/wifilight/apsetting/model/ATCommand$CMDModeTryer:this$0	Lcom/irainxun/wifilight/apsetting/model/ATCommand;
    //   96: invokestatic 29	com/irainxun/wifilight/apsetting/model/ATCommand:access$0	(Lcom/irainxun/wifilight/apsetting/model/ATCommand;)Ljava/lang/StringBuffer;
    //   99: invokevirtual 76	java/lang/StringBuilder:append	(Ljava/lang/Object;)Ljava/lang/StringBuilder;
    //   102: invokevirtual 80	java/lang/StringBuilder:toString	()Ljava/lang/String;
    //   105: invokestatic 86	android/util/Log:d	(Ljava/lang/String;Ljava/lang/String;)I
    //   108: pop
    //   109: aload_0
    //   110: getfield 10	com/irainxun/wifilight/apsetting/model/ATCommand$CMDModeTryer:this$0	Lcom/irainxun/wifilight/apsetting/model/ATCommand;
    //   113: invokestatic 29	com/irainxun/wifilight/apsetting/model/ATCommand:access$0	(Lcom/irainxun/wifilight/apsetting/model/ATCommand;)Ljava/lang/StringBuffer;
    //   116: invokevirtual 90	java/lang/StringBuffer:length	()I
    //   119: ifne +24 -> 143
    //   122: aload_0
    //   123: iconst_0
    //   124: invokevirtual 57	com/irainxun/wifilight/apsetting/model/ATCommand$CMDModeTryer:onResult	(Z)V
    //   127: return
    //   128: astore 4
    //   130: aload 4
    //   132: invokevirtual 93	java/lang/InterruptedException:printStackTrace	()V
    //   135: goto -56 -> 79
    //   138: astore_3
    //   139: aload_2
    //   140: monitorexit
    //   141: aload_3
    //   142: athrow
    //   143: aload_0
    //   144: getfield 10	com/irainxun/wifilight/apsetting/model/ATCommand$CMDModeTryer:this$0	Lcom/irainxun/wifilight/apsetting/model/ATCommand;
    //   147: invokestatic 29	com/irainxun/wifilight/apsetting/model/ATCommand:access$0	(Lcom/irainxun/wifilight/apsetting/model/ATCommand;)Ljava/lang/StringBuffer;
    //   150: invokevirtual 94	java/lang/StringBuffer:toString	()Ljava/lang/String;
    //   153: ldc 96
    //   155: invokevirtual 102	java/lang/String:split	(Ljava/lang/String;)[Ljava/lang/String;
    //   158: astore 6
    //   160: aload 6
    //   162: ifnull +173 -> 335
    //   165: aload 6
    //   167: arraylength
    //   168: ifle +167 -> 335
    //   171: aload 6
    //   173: iconst_0
    //   174: aaload
    //   175: invokestatic 107	com/irainxun/wifilight/apsetting/utils/Utils:isIP	(Ljava/lang/String;)Z
    //   178: ifeq +157 -> 335
    //   181: aload_0
    //   182: getfield 10	com/irainxun/wifilight/apsetting/model/ATCommand$CMDModeTryer:this$0	Lcom/irainxun/wifilight/apsetting/model/ATCommand;
    //   185: invokestatic 38	com/irainxun/wifilight/apsetting/model/ATCommand:access$1	(Lcom/irainxun/wifilight/apsetting/model/ATCommand;)Lcom/irainxun/wifilight/apsetting/net/UdpUnicast;
    //   188: ldc 109
    //   190: invokevirtual 55	com/irainxun/wifilight/apsetting/net/UdpUnicast:send	(Ljava/lang/String;)Z
    //   193: pop
    //   194: aload_0
    //   195: getfield 10	com/irainxun/wifilight/apsetting/model/ATCommand$CMDModeTryer:this$0	Lcom/irainxun/wifilight/apsetting/model/ATCommand;
    //   198: invokestatic 29	com/irainxun/wifilight/apsetting/model/ATCommand:access$0	(Lcom/irainxun/wifilight/apsetting/model/ATCommand;)Ljava/lang/StringBuffer;
    //   201: astore 8
    //   203: aload 8
    //   205: monitorenter
    //   206: aload_0
    //   207: getfield 10	com/irainxun/wifilight/apsetting/model/ATCommand$CMDModeTryer:this$0	Lcom/irainxun/wifilight/apsetting/model/ATCommand;
    //   210: invokestatic 29	com/irainxun/wifilight/apsetting/model/ATCommand:access$0	(Lcom/irainxun/wifilight/apsetting/model/ATCommand;)Ljava/lang/StringBuffer;
    //   213: ldc2_w 58
    //   216: invokevirtual 63	java/lang/Object:wait	(J)V
    //   219: aload 8
    //   221: monitorexit
    //   222: aload_0
    //   223: getfield 10	com/irainxun/wifilight/apsetting/model/ATCommand$CMDModeTryer:this$0	Lcom/irainxun/wifilight/apsetting/model/ATCommand;
    //   226: invokestatic 29	com/irainxun/wifilight/apsetting/model/ATCommand:access$0	(Lcom/irainxun/wifilight/apsetting/model/ATCommand;)Ljava/lang/StringBuffer;
    //   229: iconst_0
    //   230: invokevirtual 35	java/lang/StringBuffer:setLength	(I)V
    //   233: aload_0
    //   234: getfield 10	com/irainxun/wifilight/apsetting/model/ATCommand$CMDModeTryer:this$0	Lcom/irainxun/wifilight/apsetting/model/ATCommand;
    //   237: invokestatic 38	com/irainxun/wifilight/apsetting/model/ATCommand:access$1	(Lcom/irainxun/wifilight/apsetting/model/ATCommand;)Lcom/irainxun/wifilight/apsetting/net/UdpUnicast;
    //   240: ldc 111
    //   242: invokevirtual 55	com/irainxun/wifilight/apsetting/net/UdpUnicast:send	(Ljava/lang/String;)Z
    //   245: pop
    //   246: aload_0
    //   247: getfield 10	com/irainxun/wifilight/apsetting/model/ATCommand$CMDModeTryer:this$0	Lcom/irainxun/wifilight/apsetting/model/ATCommand;
    //   250: invokestatic 29	com/irainxun/wifilight/apsetting/model/ATCommand:access$0	(Lcom/irainxun/wifilight/apsetting/model/ATCommand;)Ljava/lang/StringBuffer;
    //   253: astore 12
    //   255: aload 12
    //   257: monitorenter
    //   258: aload_0
    //   259: getfield 10	com/irainxun/wifilight/apsetting/model/ATCommand$CMDModeTryer:this$0	Lcom/irainxun/wifilight/apsetting/model/ATCommand;
    //   262: invokestatic 29	com/irainxun/wifilight/apsetting/model/ATCommand:access$0	(Lcom/irainxun/wifilight/apsetting/model/ATCommand;)Ljava/lang/StringBuffer;
    //   265: ldc2_w 112
    //   268: invokevirtual 63	java/lang/Object:wait	(J)V
    //   271: aload 12
    //   273: monitorexit
    //   274: aload_0
    //   275: getfield 10	com/irainxun/wifilight/apsetting/model/ATCommand$CMDModeTryer:this$0	Lcom/irainxun/wifilight/apsetting/model/ATCommand;
    //   278: invokestatic 29	com/irainxun/wifilight/apsetting/model/ATCommand:access$0	(Lcom/irainxun/wifilight/apsetting/model/ATCommand;)Ljava/lang/StringBuffer;
    //   281: invokevirtual 90	java/lang/StringBuffer:length	()I
    //   284: ifeq +45 -> 329
    //   287: aload_0
    //   288: iconst_1
    //   289: invokevirtual 57	com/irainxun/wifilight/apsetting/model/ATCommand$CMDModeTryer:onResult	(Z)V
    //   292: return
    //   293: astore 10
    //   295: aload 10
    //   297: invokevirtual 93	java/lang/InterruptedException:printStackTrace	()V
    //   300: goto -81 -> 219
    //   303: astore 9
    //   305: aload 8
    //   307: monitorexit
    //   308: aload 9
    //   310: athrow
    //   311: astore 14
    //   313: aload 14
    //   315: invokevirtual 93	java/lang/InterruptedException:printStackTrace	()V
    //   318: goto -47 -> 271
    //   321: astore 13
    //   323: aload 12
    //   325: monitorexit
    //   326: aload 13
    //   328: athrow
    //   329: aload_0
    //   330: iconst_0
    //   331: invokevirtual 57	com/irainxun/wifilight/apsetting/model/ATCommand$CMDModeTryer:onResult	(Z)V
    //   334: return
    //   335: aload_0
    //   336: iconst_0
    //   337: invokevirtual 57	com/irainxun/wifilight/apsetting/model/ATCommand$CMDModeTryer:onResult	(Z)V
    //   340: return
    //
    // Exception table:
    //   from	to	target	type
    //   66	79	128	java/lang/InterruptedException
    //   43	65	138	finally
    //   66	79	138	finally
    //   79	81	138	finally
    //   130	135	138	finally
    //   139	141	138	finally
    //   206	219	293	java/lang/InterruptedException
    //   206	219	303	finally
    //   219	222	303	finally
    //   295	300	303	finally
    //   305	308	303	finally
    //   258	271	311	java/lang/InterruptedException
    //   258	271	321	finally
    //   271	274	321	finally
    //   313	318	321	finally
    //   323	326	321	finally
  }
}

/* Location:
 * Qualified Name:     com.irainxun.wifilight.apsetting.model.ATCommand.CMDModeTryer
 * Java Class Version: 6 (50.0)
 * JD-Core Version:    0.6.1-SNAPSHOT
 */