package com.example.smartlinklib;

class SmartLinkManipulator$1
  implements Runnable
{
  SmartLinkManipulator$1(SmartLinkManipulator paramSmartLinkManipulator)
  {
  }

  // ERROR //
  public void run()
  {
    // Byte code:
    //   0: ldc2_w 21
    //   3: invokestatic 28	java/lang/Thread:sleep	(J)V
    //   6: iconst_0
    //   7: istore_2
    //   8: iload_2
    //   9: bipush 20
    //   11: if_icmpge +13 -> 24
    //   14: aload_0
    //   15: getfield 14	com/example/smartlinklib/SmartLinkManipulator$1:this$0	Lcom/example/smartlinklib/SmartLinkManipulator;
    //   18: getfield 32	com/example/smartlinklib/SmartLinkManipulator:isConnecting	Z
    //   21: ifne +69 -> 90
    //   24: aload_0
    //   25: getfield 14	com/example/smartlinklib/SmartLinkManipulator$1:this$0	Lcom/example/smartlinklib/SmartLinkManipulator;
    //   28: getfield 32	com/example/smartlinklib/SmartLinkManipulator:isConnecting	Z
    //   31: ifeq +30 -> 61
    //   34: aload_0
    //   35: getfield 14	com/example/smartlinklib/SmartLinkManipulator$1:this$0	Lcom/example/smartlinklib/SmartLinkManipulator;
    //   38: invokestatic 36	com/example/smartlinklib/SmartLinkManipulator:access$0	(Lcom/example/smartlinklib/SmartLinkManipulator;)Ljava/util/Set;
    //   41: invokeinterface 42 1 0
    //   46: ifgt +73 -> 119
    //   49: aload_0
    //   50: getfield 14	com/example/smartlinklib/SmartLinkManipulator$1:this$0	Lcom/example/smartlinklib/SmartLinkManipulator;
    //   53: invokestatic 46	com/example/smartlinklib/SmartLinkManipulator:access$1	(Lcom/example/smartlinklib/SmartLinkManipulator;)Lcom/example/smartlinklib/SmartLinkManipulator$ConnectCallBack;
    //   56: invokeinterface 51 1 0
    //   61: aload_0
    //   62: getfield 14	com/example/smartlinklib/SmartLinkManipulator$1:this$0	Lcom/example/smartlinklib/SmartLinkManipulator;
    //   65: invokestatic 55	com/example/smartlinklib/SmartLinkManipulator:access$2	(Lcom/example/smartlinklib/SmartLinkManipulator;)Ljava/lang/String;
    //   68: ldc 57
    //   70: invokestatic 63	android/util/Log:e	(Ljava/lang/String;Ljava/lang/String;)I
    //   73: pop
    //   74: aload_0
    //   75: getfield 14	com/example/smartlinklib/SmartLinkManipulator$1:this$0	Lcom/example/smartlinklib/SmartLinkManipulator;
    //   78: iconst_0
    //   79: invokestatic 67	com/example/smartlinklib/SmartLinkManipulator:access$3	(Lcom/example/smartlinklib/SmartLinkManipulator;Z)V
    //   82: aload_0
    //   83: getfield 14	com/example/smartlinklib/SmartLinkManipulator$1:this$0	Lcom/example/smartlinklib/SmartLinkManipulator;
    //   86: invokevirtual 70	com/example/smartlinklib/SmartLinkManipulator:StopConnection	()V
    //   89: return
    //   90: aload_0
    //   91: getfield 14	com/example/smartlinklib/SmartLinkManipulator$1:this$0	Lcom/example/smartlinklib/SmartLinkManipulator;
    //   94: invokevirtual 73	com/example/smartlinklib/SmartLinkManipulator:sendFindCmd	()V
    //   97: aload_0
    //   98: getfield 14	com/example/smartlinklib/SmartLinkManipulator$1:this$0	Lcom/example/smartlinklib/SmartLinkManipulator;
    //   101: getfield 32	com/example/smartlinklib/SmartLinkManipulator:isConnecting	Z
    //   104: ifeq +9 -> 113
    //   107: ldc2_w 74
    //   110: invokestatic 28	java/lang/Thread:sleep	(J)V
    //   113: iinc 2 1
    //   116: goto -108 -> 8
    //   119: aload_0
    //   120: getfield 14	com/example/smartlinklib/SmartLinkManipulator$1:this$0	Lcom/example/smartlinklib/SmartLinkManipulator;
    //   123: invokestatic 36	com/example/smartlinklib/SmartLinkManipulator:access$0	(Lcom/example/smartlinklib/SmartLinkManipulator;)Ljava/util/Set;
    //   126: invokeinterface 42 1 0
    //   131: ifle -70 -> 61
    //   134: aload_0
    //   135: getfield 14	com/example/smartlinklib/SmartLinkManipulator$1:this$0	Lcom/example/smartlinklib/SmartLinkManipulator;
    //   138: invokestatic 46	com/example/smartlinklib/SmartLinkManipulator:access$1	(Lcom/example/smartlinklib/SmartLinkManipulator;)Lcom/example/smartlinklib/SmartLinkManipulator$ConnectCallBack;
    //   141: invokeinterface 78 1 0
    //   146: goto -85 -> 61
    //   149: astore_1
    //   150: goto -144 -> 6
    //   153: astore 4
    //   155: goto -42 -> 113
    //
    // Exception table:
    //   from	to	target	type
    //   0	6	149	java/lang/InterruptedException
    //   107	113	153	java/lang/InterruptedException
  }
}

/* Location:
 * Qualified Name:     com.example.smartlinklib.SmartLinkManipulator.1
 * Java Class Version: 6 (50.0)
 * JD-Core Version:    0.6.1-SNAPSHOT
 */