package com.irainxun.wifilight.apsetting.net;

class TCPClient$1
  implements Runnable
{
  TCPClient$1(TCPClient paramTCPClient)
  {
  }

  // ERROR //
  public void run()
  {
    // Byte code:
    //   0: aload_0
    //   1: getfield 17	com/irainxun/wifilight/apsetting/net/TCPClient$1:this$0	Lcom/irainxun/wifilight/apsetting/net/TCPClient;
    //   4: invokestatic 31	com/irainxun/wifilight/apsetting/net/TCPClient:access$0	(Lcom/irainxun/wifilight/apsetting/net/TCPClient;)Ljava/net/Socket;
    //   7: new 33	java/net/InetSocketAddress
    //   10: dup
    //   11: aload_0
    //   12: getfield 17	com/irainxun/wifilight/apsetting/net/TCPClient$1:this$0	Lcom/irainxun/wifilight/apsetting/net/TCPClient;
    //   15: invokestatic 37	com/irainxun/wifilight/apsetting/net/TCPClient:access$1	(Lcom/irainxun/wifilight/apsetting/net/TCPClient;)Ljava/lang/String;
    //   18: aload_0
    //   19: getfield 17	com/irainxun/wifilight/apsetting/net/TCPClient$1:this$0	Lcom/irainxun/wifilight/apsetting/net/TCPClient;
    //   22: invokestatic 41	com/irainxun/wifilight/apsetting/net/TCPClient:access$2	(Lcom/irainxun/wifilight/apsetting/net/TCPClient;)I
    //   25: invokespecial 44	java/net/InetSocketAddress:<init>	(Ljava/lang/String;I)V
    //   28: sipush 5000
    //   31: invokevirtual 50	java/net/Socket:connect	(Ljava/net/SocketAddress;I)V
    //   34: aload_0
    //   35: getfield 17	com/irainxun/wifilight/apsetting/net/TCPClient$1:this$0	Lcom/irainxun/wifilight/apsetting/net/TCPClient;
    //   38: new 52	java/io/BufferedInputStream
    //   41: dup
    //   42: aload_0
    //   43: getfield 17	com/irainxun/wifilight/apsetting/net/TCPClient$1:this$0	Lcom/irainxun/wifilight/apsetting/net/TCPClient;
    //   46: invokestatic 31	com/irainxun/wifilight/apsetting/net/TCPClient:access$0	(Lcom/irainxun/wifilight/apsetting/net/TCPClient;)Ljava/net/Socket;
    //   49: invokevirtual 56	java/net/Socket:getInputStream	()Ljava/io/InputStream;
    //   52: invokespecial 59	java/io/BufferedInputStream:<init>	(Ljava/io/InputStream;)V
    //   55: invokestatic 63	com/irainxun/wifilight/apsetting/net/TCPClient:access$3	(Lcom/irainxun/wifilight/apsetting/net/TCPClient;Ljava/io/BufferedInputStream;)V
    //   58: aload_0
    //   59: getfield 17	com/irainxun/wifilight/apsetting/net/TCPClient$1:this$0	Lcom/irainxun/wifilight/apsetting/net/TCPClient;
    //   62: new 65	java/io/BufferedOutputStream
    //   65: dup
    //   66: aload_0
    //   67: getfield 17	com/irainxun/wifilight/apsetting/net/TCPClient$1:this$0	Lcom/irainxun/wifilight/apsetting/net/TCPClient;
    //   70: invokestatic 31	com/irainxun/wifilight/apsetting/net/TCPClient:access$0	(Lcom/irainxun/wifilight/apsetting/net/TCPClient;)Ljava/net/Socket;
    //   73: invokevirtual 69	java/net/Socket:getOutputStream	()Ljava/io/OutputStream;
    //   76: invokespecial 72	java/io/BufferedOutputStream:<init>	(Ljava/io/OutputStream;)V
    //   79: invokestatic 76	com/irainxun/wifilight/apsetting/net/TCPClient:access$4	(Lcom/irainxun/wifilight/apsetting/net/TCPClient;Ljava/io/BufferedOutputStream;)V
    //   82: aload_0
    //   83: getfield 17	com/irainxun/wifilight/apsetting/net/TCPClient$1:this$0	Lcom/irainxun/wifilight/apsetting/net/TCPClient;
    //   86: invokestatic 80	com/irainxun/wifilight/apsetting/net/TCPClient:access$5	(Lcom/irainxun/wifilight/apsetting/net/TCPClient;)Lcom/irainxun/wifilight/apsetting/net/TCPClient$TCPClientListener;
    //   89: ifnull +16 -> 105
    //   92: aload_0
    //   93: getfield 17	com/irainxun/wifilight/apsetting/net/TCPClient$1:this$0	Lcom/irainxun/wifilight/apsetting/net/TCPClient;
    //   96: invokestatic 80	com/irainxun/wifilight/apsetting/net/TCPClient:access$5	(Lcom/irainxun/wifilight/apsetting/net/TCPClient;)Lcom/irainxun/wifilight/apsetting/net/TCPClient$TCPClientListener;
    //   99: iconst_1
    //   100: invokeinterface 86 2 0
    //   105: aload_0
    //   106: getfield 17	com/irainxun/wifilight/apsetting/net/TCPClient$1:this$0	Lcom/irainxun/wifilight/apsetting/net/TCPClient;
    //   109: invokestatic 90	com/irainxun/wifilight/apsetting/net/TCPClient:access$6	(Lcom/irainxun/wifilight/apsetting/net/TCPClient;)Ljava/io/BufferedInputStream;
    //   112: aload_0
    //   113: getfield 17	com/irainxun/wifilight/apsetting/net/TCPClient$1:this$0	Lcom/irainxun/wifilight/apsetting/net/TCPClient;
    //   116: invokestatic 94	com/irainxun/wifilight/apsetting/net/TCPClient:access$7	(Lcom/irainxun/wifilight/apsetting/net/TCPClient;)[B
    //   119: invokevirtual 98	java/io/BufferedInputStream:read	([B)I
    //   122: istore_3
    //   123: iload_3
    //   124: ifle +18 -> 142
    //   127: aload_0
    //   128: getfield 17	com/irainxun/wifilight/apsetting/net/TCPClient$1:this$0	Lcom/irainxun/wifilight/apsetting/net/TCPClient;
    //   131: aload_0
    //   132: getfield 17	com/irainxun/wifilight/apsetting/net/TCPClient$1:this$0	Lcom/irainxun/wifilight/apsetting/net/TCPClient;
    //   135: invokestatic 94	com/irainxun/wifilight/apsetting/net/TCPClient:access$7	(Lcom/irainxun/wifilight/apsetting/net/TCPClient;)[B
    //   138: iload_3
    //   139: invokevirtual 102	com/irainxun/wifilight/apsetting/net/TCPClient:onReceive	([BI)V
    //   142: ldc2_w 103
    //   145: invokestatic 110	java/lang/Thread:sleep	(J)V
    //   148: goto -43 -> 105
    //   151: astore 4
    //   153: aload 4
    //   155: invokevirtual 113	java/lang/InterruptedException:printStackTrace	()V
    //   158: goto -53 -> 105
    //   161: astore_1
    //   162: aload_1
    //   163: invokevirtual 114	java/io/IOException:printStackTrace	()V
    //   166: aload_0
    //   167: getfield 17	com/irainxun/wifilight/apsetting/net/TCPClient$1:this$0	Lcom/irainxun/wifilight/apsetting/net/TCPClient;
    //   170: invokestatic 80	com/irainxun/wifilight/apsetting/net/TCPClient:access$5	(Lcom/irainxun/wifilight/apsetting/net/TCPClient;)Lcom/irainxun/wifilight/apsetting/net/TCPClient$TCPClientListener;
    //   173: iconst_0
    //   174: invokeinterface 86 2 0
    //   179: return
    //   180: astore_2
    //   181: return
    //
    // Exception table:
    //   from	to	target	type
    //   142	148	151	java/lang/InterruptedException
    //   0	105	161	java/io/IOException
    //   105	123	161	java/io/IOException
    //   127	142	161	java/io/IOException
    //   142	148	161	java/io/IOException
    //   153	158	161	java/io/IOException
    //   105	123	180	java/lang/Exception
    //   127	142	180	java/lang/Exception
  }
}

/* Location:
 * Qualified Name:     com.irainxun.wifilight.apsetting.net.TCPClient.1
 * Java Class Version: 6 (50.0)
 * JD-Core Version:    0.6.1-SNAPSHOT
 */